LICENSE.md
MANIFEST.in
README.md
requirements.txt
setup.cfg
setup.py
pandas_explode/__init__.py
pandas_explode.egg-info/PKG-INFO
pandas_explode.egg-info/SOURCES.txt
pandas_explode.egg-info/dependency_links.txt
pandas_explode.egg-info/requires.txt
pandas_explode.egg-info/top_level.txt