Metadata-Version: 2.1
Name: pandas-explode
Version: 0.0.7
Summary: Explode utility for Pandas dataframes (similar to UNNEST or explode)
Home-page: https://github.com/orenovadia/pandas_explode
Download-URL: https://github.com/orenovadia/pandas_explode/tarball/0.0.7
Author: Oren Ovadia
Author-email: orenovad@gmail.com
License: MIT
Classifier: Development Status :: 3 - Alpha
Classifier: Intended Audience :: Developers
Classifier: Programming Language :: Python :: 3
License-File: LICENSE.md
